{
  "timeframe": 5,
  "trained_at": "2026-04-25T21:22:40.641127",
  "symbols_count": 51,
  "total_samples": 21726,
  "train_samples": 16294,
  "test_samples": 2716,
  "classifier": {
    "accuracy": 0.5773,
    "precision": 0.4456,
    "recall": 0.3996,
    "f1": 0.4214,
    "pos_rate_train": 0.4232,
    "pos_rate_test": 0.3851
  },
  "regressor": {
    "rmse": 0.045258,
    "mae": 0.03387,
    "directional_accuracy": 0.5707
  },
  "feature_importances": [
    {
      "name": "month_cos",
      "importance": 0.03424
    },
    {
      "name": "month_sin",
      "importance": 0.02799
    },
    {
      "name": "quarter_end_proximity",
      "importance": 0.0278
    },
    {
      "name": "beta",
      "importance": 0.02497
    },
    {
      "name": "dividend_yield",
      "importance": 0.02439
    },
    {
      "name": "revenue_growth",
      "importance": 0.02432
    },
    {
      "name": "macd",
      "importance": 0.02407
    },
    {
      "name": "atr_14",
      "importance": 0.02177
    },
    {
      "name": "roa",
      "importance": 0.01897
    },
    {
      "name": "insider_buy_ratio",
      "importance": 0.01801
    },
    {
      "name": "analyst_score",
      "importance": 0.01797
    },
    {
      "name": "macd_histogram",
      "importance": 0.01793
    },
    {
      "name": "gross_margin",
      "importance": 0.01781
    },
    {
      "name": "debt_to_equity",
      "importance": 0.01781
    },
    {
      "name": "dist_from_high_52w",
      "importance": 0.01771
    },
    {
      "name": "dist_from_low_52w",
      "importance": 0.01771
    },
    {
      "name": "earnings_growth",
      "importance": 0.01768
    },
    {
      "name": "macd_signal",
      "importance": 0.01753
    },
    {
      "name": "analyst_momentum",
      "importance": 0.01744
    },
    {
      "name": "vol_10d",
      "importance": 0.01733
    },
    {
      "name": "adx_14",
      "importance": 0.01723
    },
    {
      "name": "operating_margin",
      "importance": 0.01708
    },
    {
      "name": "dist_from_sma50",
      "importance": 0.01702
    },
    {
      "name": "price_percentile_52w",
      "importance": 0.01689
    },
    {
      "name": "vol_20d",
      "importance": 0.01676
    },
    {
      "name": "profit_margin",
      "importance": 0.0167
    },
    {
      "name": "trailing_pe",
      "importance": 0.01668
    },
    {
      "name": "return_20d",
      "importance": 0.01646
    },
    {
      "name": "return_10d",
      "importance": 0.0163
    },
    {
      "name": "forward_pe",
      "importance": 0.01596
    }
  ],
  "feature_columns": [
    "return_1d",
    "return_3d",
    "return_5d",
    "return_10d",
    "return_20d",
    "vol_5d",
    "vol_10d",
    "vol_20d",
    "volume_ratio_20d",
    "volume_trend_5d",
    "dist_from_high_52w",
    "dist_from_low_52w",
    "dist_from_sma20",
    "dist_from_sma50",
    "price_percentile_52w",
    "gap_pct",
    "atr_14",
    "range_ratio",
    "rsi_14",
    "rsi_oversold",
    "rsi_overbought",
    "macd",
    "macd_signal",
    "macd_histogram",
    "macd_crossover",
    "bb_position",
    "bb_bandwidth",
    "sma20_above_sma50",
    "sma_crossover",
    "adx_14",
    "plus_di",
    "minus_di",
    "stoch_k",
    "stoch_d",
    "williams_r",
    "cci_20",
    "roc_10",
    "roc_20",
    "trailing_pe",
    "forward_pe",
    "peg_ratio",
    "pe_spread",
    "profit_margin",
    "operating_margin",
    "gross_margin",
    "debt_to_equity",
    "roe",
    "roa",
    "revenue_growth",
    "earnings_growth",
    "dividend_yield",
    "beta",
    "analyst_score",
    "analyst_momentum",
    "insider_buy_ratio",
    "insider_net_shares",
    "put_call_ratio",
    "day_of_week_sin",
    "day_of_week_cos",
    "month_sin",
    "month_cos",
    "quarter_end_proximity"
  ]
}